tno/mpc/encryption_schemes/utils/__init__.py
tno/mpc/encryption_schemes/utils/_check_gmpy2.py
tno/mpc/encryption_schemes/utils/fixed_point.py
tno/mpc/encryption_schemes/utils/py.typed
tno/mpc/encryption_schemes/utils/utils.py
tno/mpc/encryption_schemes/utils/test/__init__.py
tno/mpc/encryption_schemes/utils/test/fixed_point_test_parameters.py
tno/mpc/encryption_schemes/utils/test/test_fixed_point.py
tno/mpc/encryption_schemes/utils/test/test_serialization.py
tno/mpc/encryption_schemes/utils/test/test_utils.py
tno_mpc_encryption_schemes_utils-0.16.1.dist-info/licenses/LICENSE
tno_mpc_encryption_schemes_utils-0.16.1.dist-info/METADATA
tno_mpc_encryption_schemes_utils-0.16.1.dist-info/WHEEL
tno_mpc_encryption_schemes_utils-0.16.1.dist-info/top_level.txt
tno_mpc_encryption_schemes_utils-0.16.1.dist-info/RECORD
