Metadata-Version: 2.4
Name: tno.mpc.encryption_schemes.utils
Version: 0.16.1
Summary: Generic utilities for implementing encryption schemes
Author-email: TNO PET Lab <petlab@tno.nl>
Maintainer-email: TNO PET Lab <petlab@tno.nl>
License: Apache License, Version 2.0
Project-URL: Homepage, https://pet.tno.nl/
Project-URL: Documentation, https://docs.pet.tno.nl/mpc/encryption_schemes/utils/0.16.1
Project-URL: Source, https://github.com/TNO-MPC/encryption_schemes.utils
Keywords: TNO,MPC,multi-party computation,encryption schemes,utils
Platform: any
Classifier: License :: OSI Approved :: Apache Software License
Classifier: Programming Language :: Python :: 3
Classifier: Operating System :: OS Independent
Classifier: Intended Audience :: Developers
Classifier: Intended Audience :: Information Technology
Classifier: Intended Audience :: Science/Research
Classifier: Typing :: Typed
Classifier: Topic :: Security :: Cryptography
Requires-Python: >=3.9
License-File: LICENSE
Requires-Dist: packaging
Requires-Dist: sympy~=1.3
Provides-Extra: communication
Requires-Dist: tno.mpc.communication~=5.0; extra == "communication"
Provides-Extra: gmpy
Requires-Dist: gmpy2>=2.1.3; extra == "gmpy"
Requires-Dist: importlib_metadata<9,>=2.1; python_version < "3.10" and extra == "gmpy"
Provides-Extra: tests
Requires-Dist: numpy; extra == "tests"
Requires-Dist: pytest>=8.1; extra == "tests"
Requires-Dist: tno.mpc.encryption_schemes.utils[communication]; extra == "tests"
Dynamic: license-file
